{"cameraMode":{"drawMode":0,"name":"Shaded","section":"Shading Mode"},"sceneLighting":true,"audioPlay":false,"sceneViewState":{"m_AlwaysRefresh":false,"showFog":true,"showSkybox":true,"showFlares":true,"showImageEffects":true,"showParticleSystems":true,"showVisualEffectGraphs":true,"m_FxEnabled":true},"in2DMode":false,"pivot":{"x":524.751220703125,"y":271.09765625,"z":963.7421264648438},"rotation":{"x":0.00269030942581594,"y":-0.011402257718145848,"z":-0.00003039395778614562,"w":-0.9999349117279053},"size":751.696533203125,"orthographic":false}